neuro_pypes/__init__.py
neuro_pypes/_utils.py
neuro_pypes/config.py
neuro_pypes/crumb.py
neuro_pypes/datasets.py
neuro_pypes/io.py
neuro_pypes/plot.py
neuro_pypes/run.py
neuro_pypes/version.py
neuro_pypes/anat/__init__.py
neuro_pypes/anat/cortex.py
neuro_pypes/anat/preproc.py
neuro_pypes/anat/utils.py
neuro_pypes/convert/__init__.py
neuro_pypes/convert/dicom_to_nifti.py
neuro_pypes/dmri/__init__.py
neuro_pypes/dmri/artifacts.py
neuro_pypes/dmri/camino.py
neuro_pypes/dmri/coregister.py
neuro_pypes/dmri/dti.py
neuro_pypes/dmri/utils.py
neuro_pypes/fmri/__init__.py
neuro_pypes/fmri/_cpac_stuff_for_ref.py
neuro_pypes/fmri/clean.py
neuro_pypes/fmri/filter.py
neuro_pypes/fmri/grouptemplate.py
neuro_pypes/fmri/nuisance.py
neuro_pypes/fmri/rest.py
neuro_pypes/fmri/utils.py
neuro_pypes/fmri/warp.py
neuro_pypes/ica/__init__.py
neuro_pypes/ica/decompose.py
neuro_pypes/ica/dual_regression.py
neuro_pypes/ica/loadings.py
neuro_pypes/ica/plotting.py
neuro_pypes/ica/rsn_atlas.py
neuro_pypes/ica/spatial_maps.py
neuro_pypes/ica/utils.py
neuro_pypes/interfaces/__init__.py
neuro_pypes/interfaces/ants/__init__.py
neuro_pypes/interfaces/ants/segmentation.py
neuro_pypes/interfaces/fsl/__init__.py
neuro_pypes/interfaces/fsl/epi.py
neuro_pypes/interfaces/nilearn/__init__.py
neuro_pypes/interfaces/nilearn/canica.py
neuro_pypes/interfaces/nilearn/connectivity.py
neuro_pypes/interfaces/nilearn/image.py
neuro_pypes/interfaces/nilearn/plot.py
neuro_pypes/interfaces/nilearn/roi.py
neuro_pypes/interfaces/nilearn/signal.py
neuro_pypes/networks/__init__.py
neuro_pypes/networks/plotting.py
neuro_pypes/pet/__init__.py
neuro_pypes/pet/grouptemplate.py
neuro_pypes/pet/mrpet.py
neuro_pypes/pet/pvc.py
neuro_pypes/pet/utils.py
neuro_pypes/pet/warp.py
neuro_pypes/preproc/__init__.py
neuro_pypes/preproc/denoise.py
neuro_pypes/preproc/dicom.py
neuro_pypes/preproc/motion_stats.py
neuro_pypes/preproc/petpvc.py
neuro_pypes/preproc/realign.py
neuro_pypes-0.3.6.dist-info/DESCRIPTION.rst
neuro_pypes-0.3.6.dist-info/METADATA
neuro_pypes-0.3.6.dist-info/RECORD
neuro_pypes-0.3.6.dist-info/WHEEL
neuro_pypes-0.3.6.dist-info/dependency_links.txt
neuro_pypes-0.3.6.dist-info/metadata.json
neuro_pypes-0.3.6.dist-info/top_level.txt
