Metadata-Version: 2.0
Name: neuro-pypes
Version: 0.3.6
Summary: Reusable and configurable neuroimaging pipelines with Nipype.
Home-page: UNKNOWN
Author: Alexandre Savio
Author-email: alexsavio@gmail.com
License: Apache License, Version 2.0
Platform: Linux/MacOSX
Classifier: Programming Language :: Python
Classifier: Development Status :: 4 - Beta
Classifier: Natural Language :: English
Classifier: Environment :: Console
Classifier: Intended Audience :: Science/Research
Classifier: License :: OSI Approved :: Apache Software License
Classifier: Operating System :: OS Independent
Classifier: Topic :: Scientific/Engineering :: Information Analysis
Classifier: Topic :: Scientific/Engineering :: Medical Science Apps.
Classifier: Operating System :: POSIX
Classifier: Operating System :: Unix
Classifier: Operating System :: MacOS
Classifier: Programming Language :: Python :: 3
Classifier: Programming Language :: Python :: 3.4
Classifier: Programming Language :: Python :: 3.5
Classifier: Programming Language :: Python :: 3.6
Requires-Dist: numpy (==1.13.3)
Requires-Dist: scipy (==1.0.0)
Requires-Dist: hansel (>=0.9.5)
Requires-Dist: matplotlib (==2.1.0)
Requires-Dist: nilearn (==0.3.1)
Requires-Dist: kaptan (==0.5.9)
Requires-Dist: nibabel (==2.2.0)
Requires-Dist: nipype (==0.13.1)
Requires-Dist: nipy
Requires-Dist: pydicom
Requires-Dist: boyle
Provides-Extra: docs
Requires-Dist: mkdocs; extra == 'docs'
Requires-Dist: recommonmark; extra == 'docs'
Provides-Extra: tests
